Metadata-Version: 1.0
Name: sgb-distribution
Version: 4.0
Summary: Gaussian and Binomial Distributions
Home-page: UNKNOWN
Author: Shivam Wankhade
Author-email: shivamwankhade12@gmail.com
License: UNKNOWN
Platform: UNKNOWN
